[{"name": "void __cdecl Charcoal::OpenGLContext::Init(void)","cat": "category","ph": "X","ts": "1058454769","dur": "18705","pid": "0","tid": "7790559108661772848"},{"name": "void __cdecl Charcoal::WindowsWindow::Init(const struct Charcoal::WindowProps &)","cat": "category","ph": "X","ts": "1057992817","dur": "481105","pid": "0","tid": "7790559108661772848"},{"name": "class Charcoal::Window *__cdecl Charcoal::Window::Create(const struct Charcoal::WindowProps &)","cat": "category","ph": "X","ts": "1057992811","dur": "481180","pid": "0","tid": "7790559108661772848"},{"name": "void __cdecl Charcoal::OpenGLRendererAPI::Init(void)","cat": "category","ph": "X","ts": "1058474082","dur": "8","pid": "0","tid": "7790559108661772848"},{"name": "class std::basic_string<char,struct std::char_traits<char>,class std::allocator<char> > __cdecl Charcoal::OpenGLShader::ReadFile(const class std::basic_string<char,struct std::char_traits<char>,class std::allocator<char> > &)","cat": "category","ph": "X","ts": "1058474197","dur": "4748","pid": "0","tid": "7790559108661772848"},{"name": "class std::unordered_map<unsigned int,class std::basic_string<char,struct std::char_traits<char>,class std::allocator<char> >,struct std::hash<unsigned int>,struct std::equal_to<unsigned int>,class std::allocator<struct std::pair<unsigned int const ,class std::basic_string<char,struct std::char_traits<char>,class std::allocator<char> > > > > __cdecl Charcoal::OpenGLShader::PreProcess(const class std::basic_string<char,struct std::char_traits<char>,class std::allocator<char> >)","cat": "category","ph": "X","ts": "1058479044","dur": "62","pid": "0","tid": "7790559108661772848"},{"name": "void __cdecl Charcoal::OpenGLShader::Compile(const class std::unordered_map<unsigned int,class std::basic_string<char,struct std::char_traits<char>,class std::allocator<char> >,struct std::hash<unsigned int>,struct std::equal_to<unsigned int>,class std::allocator<struct std::pair<unsigned int const ,class std::basic_string<char,struct std::char_traits<char>,class std::allocator<char> > > > > &)","cat": "category","ph": "X","ts": "1058479170","dur": "1157","pid": "0","tid": "7790559108661772848"},{"name": "__cdecl Charcoal::OpenGLShader::OpenGLShader(const class std::basic_string<char,struct std::char_traits<char>,class std::allocator<char> > &)","cat": "category","ph": "X","ts": "1058474195","dur": "6278","pid": "0","tid": "7790559108661772848"},{"name": "__cdecl Charcoal::OpenGLVertexArray::OpenGLVertexArray(void)","cat": "category","ph": "X","ts": "1058480549","dur": "32","pid": "0","tid": "7790559108661772848"},{"name": "__cdecl Charcoal::OpenGLVertexBuffer::OpenGLVertexBuffer(unsigned int,float *)","cat": "category","ph": "X","ts": "1058480673","dur": "284","pid": "0","tid": "7790559108661772848"},{"name": "__cdecl Charcoal::OpenGLIndexBuffer::OpenGLIndexBuffer(unsigned int,unsigned int *)","cat": "category","ph": "X","ts": "1058481053","dur": "6","pid": "0","tid": "7790559108661772848"},{"name": "void __cdecl Charcoal::OpenGLVertexBuffer::Bind(void) const","cat": "category","ph": "X","ts": "1058481139","dur": "0","pid": "0","tid": "7790559108661772848"},{"name": "void __cdecl Charcoal::OpenGLVertexArray::AddVertexBuffer(const class std::shared_ptr<class Charcoal::VertexBuffer>)","cat": "category","ph": "X","ts": "1058481130","dur": "99","pid": "0","tid": "7790559108661772848"},{"name": "void __cdecl Charcoal::OpenGLIndexBuffer::Bind(void) const","cat": "category","ph": "X","ts": "1058481288","dur": "1","pid": "0","tid": "7790559108661772848"},{"name": "void __cdecl Charcoal::OpenGLVertexArray::SetIndexBuffer(const class std::shared_ptr<class Charcoal::IndexBuffer>)","cat": "category","ph": "X","ts": "1058481287","dur": "58","pid": "0","tid": "7790559108661772848"},{"name": "__cdecl Charcoal::OpenGLTexture2D::OpenGLTexture2D(unsigned int,unsigned int,const struct glm::vec<4,float,0> &)","cat": "category","ph": "X","ts": "1058481415","dur": "923","pid": "0","tid": "7790559108661772848"},{"name": "void __cdecl Charcoal::Renderer2D::Init(void)","cat": "category","ph": "X","ts": "1058474148","dur": "8328","pid": "0","tid": "7790559108661772848"},{"name": "void __cdecl Charcoal::ImGuiLayer::OnAttach(void)","cat": "category","ph": "X","ts": "1058482640","dur": "219","pid": "0","tid": "7790559108661772848"},{"name": "__cdecl Charcoal::Application::Application(void)","cat": "category","ph": "X","ts": "1057992799","dur": "490147","pid": "0","tid": "7790559108661772848"},{"name": "__cdecl Charcoal::OrthographicCamera::OrthographicCamera(float)","cat": "category","ph": "X","ts": "1058483013","dur": "14","pid": "0","tid": "7790559108661772848"},{"name": "__cdecl Charcoal::OpenGLVertexArray::OpenGLVertexArray(void)","cat": "category","ph": "X","ts": "1058483132","dur": "13","pid": "0","tid": "7790559108661772848"},{"name": "void __cdecl Charcoal::OpenGLVertexArray::Bind(void) const","cat": "category","ph": "X","ts": "1058483214","dur": "6","pid": "0","tid": "7790559108661772848"},{"name": "__cdecl Charcoal::OpenGLVertexBuffer::OpenGLVertexBuffer(unsigned int,float *)","cat": "category","ph": "X","ts": "1058483292","dur": "72","pid": "0","tid": "7790559108661772848"},{"name": "__cdecl Charcoal::OpenGLIndexBuffer::OpenGLIndexBuffer(unsigned int,unsigned int *)","cat": "category","ph": "X","ts": "1058483437","dur": "4","pid": "0","tid": "7790559108661772848"},{"name": "void __cdecl Charcoal::OpenGLVertexBuffer::Bind(void) const","cat": "category","ph": "X","ts": "1058483503","dur": "1","pid": "0","tid": "7790559108661772848"},{"name": "void __cdecl Charcoal::OpenGLVertexArray::AddVertexBuffer(const class std::shared_ptr<class Charcoal::VertexBuffer>)","cat": "category","ph": "X","ts": "1058483501","dur": "68","pid": "0","tid": "7790559108661772848"},{"name": "void __cdecl Charcoal::OpenGLIndexBuffer::Bind(void) const","cat": "category","ph": "X","ts": "1058483630","dur": "1","pid": "0","tid": "7790559108661772848"},{"name": "void __cdecl Charcoal::OpenGLVertexArray::SetIndexBuffer(const class std::shared_ptr<class Charcoal::IndexBuffer>)","cat": "category","ph": "X","ts": "1058483629","dur": "57","pid": "0","tid": "7790559108661772848"},{"name": "class std::basic_string<char,struct std::char_traits<char>,class std::allocator<char> > __cdecl Charcoal::OpenGLShader::ReadFile(const class std::basic_string<char,struct std::char_traits<char>,class std::allocator<char> > &)","cat": "category","ph": "X","ts": "1058483759","dur": "190","pid": "0","tid": "7790559108661772848"},{"name": "class std::unordered_map<unsigned int,class std::basic_string<char,struct std::char_traits<char>,class std::allocator<char> >,struct std::hash<unsigned int>,struct std::equal_to<unsigned int>,class std::allocator<struct std::pair<unsigned int const ,class std::basic_string<char,struct std::char_traits<char>,class std::allocator<char> > > > > __cdecl Charcoal::OpenGLShader::PreProcess(const class std::basic_string<char,struct std::char_traits<char>,class std::allocator<char> >)","cat": "category","ph": "X","ts": "1058484017","dur": "94","pid": "0","tid": "7790559108661772848"},{"name": "void __cdecl Charcoal::OpenGLShader::Compile(const class std::unordered_map<unsigned int,class std::basic_string<char,struct std::char_traits<char>,class std::allocator<char> >,struct std::hash<unsigned int>,struct std::equal_to<unsigned int>,class std::allocator<struct std::pair<unsigned int const ,class std::basic_string<char,struct std::char_traits<char>,class std::allocator<char> > > > > &)","cat": "category","ph": "X","ts": "1058484175","dur": "97","pid": "0","tid": "7790559108661772848"},{"name": "__cdecl Charcoal::OpenGLShader::OpenGLShader(const class std::basic_string<char,struct std::char_traits<char>,class std::allocator<char> > &)","cat": "category","ph": "X","ts": "1058483758","dur": "589","pid": "0","tid": "7790559108661772848"},{"name": "unsigned int __cdecl Charcoal::OpenGLShader::GetUniformLocation(const class std::basic_string<char,struct std::char_traits<char>,class std::allocator<char> > &) const","cat": "category","ph": "X","ts": "1058484432","dur": "27","pid": "0","tid": "7790559108661772848"},{"name": "OpenGLTexture2D : stbi_load","cat": "category","ph": "X","ts": "1058484549","dur": "18250","pid": "0","tid": "7790559108661772848"},{"name": "__cdecl Charcoal::OpenGLTexture2D::OpenGLTexture2D(const class std::basic_string<char,struct std::char_traits<char>,class std::allocator<char> > &)","cat": "category","ph": "X","ts": "1058484548","dur": "20280","pid": "0","tid": "7790559108661772848"},{"name": "OpenGLTexture2D : stbi_load","cat": "category","ph": "X","ts": "1058505045","dur": "27668","pid": "0","tid": "7790559108661772848"},{"name": "__cdecl Charcoal::OpenGLTexture2D::OpenGLTexture2D(const class std::basic_string<char,struct std::char_traits<char>,class std::allocator<char> > &)","cat": "category","ph": "X","ts": "1058505044","dur": "29681","pid": "0","tid": "7790559108661772848"},{"name": "void __cdecl Sandbox2D::OnAttach(void)","cat": "category","ph": "X","ts": "1058483114","dur": "51911","pid": "0","tid": "7790559108661772848"}]